secure_test_pack/__init__.py
secure_test_pack/sample.py
my_secure_test_package-0.0.2.dist-info/METADATA
my_secure_test_package-0.0.2.dist-info/WHEEL
my_secure_test_package-0.0.2.dist-info/top_level.txt
my_secure_test_package-0.0.2.dist-info/RECORD
